hmd_lib_robot_shared/__init__.py
hmd_lib_robot_shared/audit_record_client_robot_lib.py
hmd_lib_robot_shared/basic_client_robot_lib.py
hmd_lib_robot_shared/containers_lib.py
hmd_lib_robot_shared/datadog_robot_lib.py
hmd_lib_robot_shared/device_provisioning_robot_lib.py
hmd_lib_robot_shared/dynamodb_client_robot_lib.py
hmd_lib_robot_shared/librarian_robot_lib.py
hmd_lib_robot_shared/postgres_client_robot_lib.py
hmd_lib_robot_shared/transform_client_robot_lib.py
hmd_lib_robot_shared/trino_robot_lib.py
hmd_lib_robot_shared-0.2.121.dist-info/METADATA
hmd_lib_robot_shared-0.2.121.dist-info/WHEEL
hmd_lib_robot_shared-0.2.121.dist-info/top_level.txt
hmd_lib_robot_shared-0.2.121.dist-info/RECORD
