Metadata-Version: 2.1
Name: hmd-lib-robot-shared
Version: 0.2.121
Summary: Shared Robotframework libraries
Author: Jim Majure
Author-email: jim.majure@hmdlabs.io
License: Apache 2.0
Requires-Dist: acachecontrol==0.3.6
Requires-Dist: aenum==3.1.15
Requires-Dist: aiohappyeyeballs==2.4.3
Requires-Dist: aiohttp==3.10.10
Requires-Dist: aiosignal==1.3.1
Requires-Dist: alembic==1.13.3
Requires-Dist: annotated-types==0.7.0
Requires-Dist: async-timeout==4.0.3
Requires-Dist: attrs==24.2.0
Requires-Dist: aws-requests-auth==0.4.3
Requires-Dist: aws-secretsmanager-caching==1.1.3
Requires-Dist: awscrt==0.27.1
Requires-Dist: backoff==2.2.1
Requires-Dist: boto3==1.36.22
Requires-Dist: botocore==1.36.23
Requires-Dist: cachetools==5.2.0
Requires-Dist: cement==3.0.6
Requires-Dist: certifi==2025.4.26
Requires-Dist: cffi==2.0.0
Requires-Dist: charset-normalizer==2.0.12
Requires-Dist: click==8.1.8
Requires-Dist: cryptography==46.0.2
Requires-Dist: datadog-api-client==1.1.0
Requires-Dist: decorator==5.2.1
Requires-Dist: durationpy==0.10
Requires-Dist: ecdsa==0.19.1
Requires-Dist: frozenlist==1.3.3
Requires-Dist: google-auth==2.9.1
Requires-Dist: greenlet==1.1.3.post0
Requires-Dist: gremlinpython==3.7.2
Requires-Dist: hmd-cli-tools~=1.2.242
Requires-Dist: hmd-entity-storage~=0.2.301
Requires-Dist: hmd-graphql-client~=0.1.158
Requires-Dist: hmd-lang-audit~=0.1.3
Requires-Dist: hmd-lang-device~=0.1.16
Requires-Dist: hmd-lang-naming~=0.1.13
Requires-Dist: hmd-lib-auth~=0.1.116
Requires-Dist: hmd-lib-containers~=0.1.83
Requires-Dist: hmd-lib-librarian-client~=0.1.101
Requires-Dist: hmd-lib-naming~=0.2.55
Requires-Dist: hmd-lib-transform~=0.1.68
Requires-Dist: hmd-meta-types~=0.2.92
Requires-Dist: hmd-schema-loader~=0.2.35
Requires-Dist: idna==3.10
Requires-Dist: inquirerpy==0.3.4
Requires-Dist: isodate==0.6.1
Requires-Dist: jmespath==0.10.0
Requires-Dist: jsonschema==4.23.0
Requires-Dist: jsonschema-specifications==2024.10.1
Requires-Dist: kubernetes==34.1.0
Requires-Dist: mako==1.3.6
Requires-Dist: markupsafe==3.0.2
Requires-Dist: multidict==6.4.3
Requires-Dist: nest-asyncio==1.6.0
Requires-Dist: oauthlib==3.3.1
Requires-Dist: okta-jwt-verifier==0.3.0
Requires-Dist: pfzy==0.3.4
Requires-Dist: prompt-toolkit==3.0.38
Requires-Dist: psycopg2-binary==2.9.10
Requires-Dist: pyasn1==0.6.1
Requires-Dist: pyasn1-modules==0.4.2
Requires-Dist: pycparser==2.23
Requires-Dist: pydantic==2.11.9
Requires-Dist: pydantic-core==2.33.2
Requires-Dist: pyjwt==2.10.1
Requires-Dist: python-dateutil==2.8.2
Requires-Dist: python-dotenv==1.1.1
Requires-Dist: python-jose==3.5.0
Requires-Dist: python-on-whales==0.78.0
Requires-Dist: pytz==2025.2
Requires-Dist: pyyaml==6.0.1
Requires-Dist: referencing==0.35.1
Requires-Dist: requests==2.32.3
Requires-Dist: requests-oauthlib==1.3.1
Requires-Dist: retry2==0.9.5
Requires-Dist: rpds-py==0.20.0
Requires-Dist: rsa==4.8
Requires-Dist: s3transfer==0.11.2
Requires-Dist: six==1.16.0
Requires-Dist: sqlalchemy==2.0.36
Requires-Dist: tqdm==4.63.0
Requires-Dist: trino==0.330.0
Requires-Dist: typing-extensions==4.15.0
Requires-Dist: typing-inspection==0.4.0
Requires-Dist: tzlocal==5.3.1
Requires-Dist: urllib3==1.26.8
Requires-Dist: wcwidth==0.2.6
Requires-Dist: websocket-client==1.3.3
Requires-Dist: yarl==1.12.0
